coverage_rich/__about__.py
coverage_rich/__init__.py
coverage_rich/__main__.py
coverage_rich/config.py
coverage_rich/console.py
coverage_rich/report.py
coverage_rich/standard_config.py
coverage_rich/cli/__init__.py
coverage_rich/cli/app.py
coverage_rich/cli/common.py
coverage_rich/cli/config.py
coverage_rich/cli/report.py
coverage_rich/cli/tui.py
coverage_rich/tui/app.css
coverage_rich/tui/app.py
coverage_rich-0.2.0.dist-info/METADATA
coverage_rich-0.2.0.dist-info/WHEEL
coverage_rich-0.2.0.dist-info/entry_points.txt
coverage_rich-0.2.0.dist-info/licenses/LICENSE.txt
coverage_rich-0.2.0.dist-info/RECORD
